project_config/__init__.py
project_config/__main__.py
project_config/cache.py
project_config/compat.py
project_config/constants.py
project_config/exceptions.py
project_config/py.typed
project_config/tree.py
project_config/types_.py
project_config/commands/__init__.py
project_config/commands/check.py
project_config/commands/clean.py
project_config/commands/fix.py
project_config/commands/init.py
project_config/commands/show.py
project_config/config/__init__.py
project_config/config/exceptions.py
project_config/config/schema.json
project_config/config/style/__init__.py
project_config/fetchers/__init__.py
project_config/fetchers/file.py
project_config/fetchers/github.py
project_config/fetchers/https.py
project_config/plugins/__init__.py
project_config/plugins/existence.py
project_config/plugins/inclusion.py
project_config/plugins/jmespath.py
project_config/plugins/contrib/__init__.py
project_config/plugins/contrib/pre_commit.py
project_config/reporters/__init__.py
project_config/reporters/base.py
project_config/reporters/default.py
project_config/reporters/ghf_markdown.py
project_config/reporters/json_.py
project_config/reporters/table.py
project_config/reporters/toml.py
project_config/reporters/yaml.py
project_config/serializers/__init__.py
project_config/serializers/editorconfig.py
project_config/serializers/ini.py
project_config/serializers/json.py
project_config/serializers/python.py
project_config/serializers/text.py
project_config/serializers/toml.py
project_config/serializers/yaml.py
project_config/serializers/contrib/__init__.py
project_config/serializers/contrib/pre_commit.py
project_config/tests/__init__.py
project_config/tests/pytest_plugin/__init__.py
project_config/tests/pytest_plugin/helpers.py
project_config/tests/pytest_plugin/plugin.py
project_config/utils/__init__.py
project_config/utils/crypto.py
project_config/utils/http.py
project_config/utils/jmespath.py
project_config-0.9.7.dist-info/METADATA
project_config-0.9.7.dist-info/WHEEL
project_config-0.9.7.dist-info/entry_points.txt
project_config-0.9.7.dist-info/licenses/LICENSE
project_config-0.9.7.dist-info/RECORD
