Metadata-Version: 2.3
Name: project-config
Version: 0.9.7
Summary: Reproducible configuration across projects.
Project-URL: Source, https://github.com/mondeja/project-config
Project-URL: Documentation, https://mondeja.github.io/project-config
Project-URL: Bug tracker, https://github.com/mondeja/project-config/issues
Project-URL: Changelog, https://github.com/mondeja/project-config/releases
Author-email: Álvaro Mondéjar Rubio <mondejar1994@gmail.com>
License-Expression: BSD-3-Clause
License-File: LICENSE
Keywords: config,configuration,linter,meta-linter,project,reproducible
Classifier: Development Status :: 4 - Beta
Classifier: Environment :: Console
Classifier: Intended Audience :: Developers
Classifier: License :: OSI Approved :: BSD License
Classifier: Operating System :: OS Independent
Classifier: Programming Language :: Python :: 3.8
Classifier: Programming Language :: Python :: 3.9
Classifier: Programming Language :: Python :: 3.10
Classifier: Programming Language :: Python :: 3.11
Classifier: Programming Language :: Python :: 3.12
Classifier: Topic :: Software Development :: Libraries :: Python Modules
Classifier: Topic :: Software Development :: Quality Assurance
Requires-Python: <3.13,>=3.8
Requires-Dist: appdirs~=1.0
Requires-Dist: colored
Requires-Dist: contextlib-chdir
Requires-Dist: deepmerge~=1.0
Requires-Dist: identify~=2.0
Requires-Dist: importlib-metadata; python_version < '3.10'
Requires-Dist: jmespath~=1.0
Requires-Dist: pyjson5
Requires-Dist: requests
Requires-Dist: requests-futures~=1.0
Requires-Dist: ruamel-yaml~=0.17
Requires-Dist: tabulate~=0.8
Requires-Dist: tomli-w~=1.0
Requires-Dist: tomli~=2.0; python_version < '3.11'
Requires-Dist: tomlkit~=0.11
